hypergumbo/__init__.py
hypergumbo/__main__.py
hypergumbo-2.0.0.dist-info/METADATA
hypergumbo-2.0.0.dist-info/WHEEL
hypergumbo-2.0.0.dist-info/entry_points.txt
hypergumbo-2.0.0.dist-info/RECORD
